gm3dh5/__about__.py
gm3dh5/__init__.py
gm3dh5/file.py
gm3dh5/file.pyi
gm3dh5/geometry.py
gm3dh5/geometry.pyi
gm3dh5/protocols.py
gm3dh5/utils.py
gm3dh5/_detail/__init__.py
gm3dh5/_detail/quaternion.py
gm3dh5/_detail/types.py
gm3dh5/_detail/utils.py
gm3dh5/_detail/vec3.py
gm3dh5/exporter/__init__.py
gm3dh5/exporter/__init__.pyi
gm3dh5/exporter/csv.py
gm3dh5/exporter/csv.pyi
gm3dh5/exporter/neper.py
gm3dh5/exporter/neper.pyi
gm3dh5-0.0.1.dist-info/METADATA
gm3dh5-0.0.1.dist-info/WHEEL
gm3dh5-0.0.1.dist-info/licenses/LICENSE
gm3dh5-0.0.1.dist-info/RECORD
