Metadata-Version: 2.3
Name: gm3dh5
Version: 0.0.1
Summary: A lightweight interface for GrainMapper3D Results Files
Project-URL: Documentation, http://xnovotech.github.io/gm3dh5/
Project-URL: Issues, https://github.com/xnovotech/gm3dh5/issues
Project-URL: Source, https://github.com/xnovotech/gm3dh5
Author-email: Florian Bachmann <fbachmann@xnovotech.com>
License:                                  Apache License
Classifier: Development Status :: 5 - Production/Stable
Classifier: Intended Audience :: Science/Research
Classifier: License :: OSI Approved :: Apache Software License
Classifier: Natural Language :: English
Classifier: Operating System :: OS Independent
Classifier: Programming Language :: Python
Classifier: Programming Language :: Python :: 3 :: Only
Classifier: Programming Language :: Python :: 3.8
Classifier: Programming Language :: Python :: 3.9
Classifier: Programming Language :: Python :: 3.10
Classifier: Programming Language :: Python :: 3.11
Classifier: Programming Language :: Python :: 3.12
Classifier: Programming Language :: Python :: Implementation :: CPython
Classifier: Topic :: Scientific/Engineering
Classifier: Topic :: Scientific/Engineering :: Physics
Classifier: Topic :: Software Development
Requires-Python: >=3.8
Requires-Dist: h5py
Requires-Dist: numpy
Provides-Extra: dev
Requires-Dist: build; extra == 'dev'
Requires-Dist: docstring-parser; extra == 'dev'
Requires-Dist: matplotlib; extra == 'dev'
Requires-Dist: numba; extra == 'dev'
Requires-Dist: numpydoc; extra == 'dev'
Requires-Dist: pydata-sphinx-theme; extra == 'dev'
Requires-Dist: scikit-image; extra == 'dev'
Requires-Dist: sphinx; extra == 'dev'
Requires-Dist: sphinx-codeautolink; extra == 'dev'
Requires-Dist: sphinx-copybutton; extra == 'dev'
Requires-Dist: sphinx-design; extra == 'dev'
Requires-Dist: sphinx-gallery; extra == 'dev'
Requires-Dist: tests; extra == 'dev'
Provides-Extra: doc
Requires-Dist: docstring-parser; extra == 'doc'
Requires-Dist: matplotlib; extra == 'doc'
Requires-Dist: numpydoc; extra == 'doc'
Requires-Dist: pydata-sphinx-theme; extra == 'doc'
Requires-Dist: scikit-image; extra == 'doc'
Requires-Dist: sphinx; extra == 'doc'
Requires-Dist: sphinx-codeautolink; extra == 'doc'
Requires-Dist: sphinx-copybutton; extra == 'doc'
Requires-Dist: sphinx-design; extra == 'doc'
Requires-Dist: sphinx-gallery; extra == 'doc'
Provides-Extra: dragonfly
Requires-Dist: h5py==2.10.0; extra == 'dragonfly'
Requires-Dist: numba==0.51.2; extra == 'dragonfly'
Requires-Dist: numpy==1.19.5; extra == 'dragonfly'
Provides-Extra: numba
Requires-Dist: numba; extra == 'numba'
Provides-Extra: tests
Requires-Dist: coverage2clover; extra == 'tests'
Requires-Dist: pytest; extra == 'tests'
Requires-Dist: pytest-cov; extra == 'tests'
Requires-Dist: pytest-rerunfailures; extra == 'tests'
Requires-Dist: pytest-xdist; extra == 'tests'
